odoo/addons/l10n_br_currency_rate_update/README.rst
odoo/addons/l10n_br_currency_rate_update/__init__.py
odoo/addons/l10n_br_currency_rate_update/__manifest__.py
odoo/addons/l10n_br_currency_rate_update/i18n/es.po
odoo/addons/l10n_br_currency_rate_update/i18n/l10n_br_currency_rate_update.pot
odoo/addons/l10n_br_currency_rate_update/i18n/pt_BR.po
odoo/addons/l10n_br_currency_rate_update/models/__init__.py
odoo/addons/l10n_br_currency_rate_update/models/res_currency_rate_provider_bcb.py
odoo/addons/l10n_br_currency_rate_update/readme/CONFIGURE.md
odoo/addons/l10n_br_currency_rate_update/readme/CONTRIBUTORS.md
odoo/addons/l10n_br_currency_rate_update/readme/DESCRIPTION.md
odoo/addons/l10n_br_currency_rate_update/readme/USAGE.md
odoo/addons/l10n_br_currency_rate_update/static/description/icon.png
odoo/addons/l10n_br_currency_rate_update/static/description/index.html
odoo/addons/l10n_br_currency_rate_update/tests/__init__.py
odoo/addons/l10n_br_currency_rate_update/tests/test_currency_rate_update_bcb.py
odoo_addon_l10n_br_currency_rate_update-18.0.1.0.0.2.dist-info/METADATA
odoo_addon_l10n_br_currency_rate_update-18.0.1.0.0.2.dist-info/WHEEL
odoo_addon_l10n_br_currency_rate_update-18.0.1.0.0.2.dist-info/top_level.txt
odoo_addon_l10n_br_currency_rate_update-18.0.1.0.0.2.dist-info/RECORD
